[
    {
        "isbn": "9782820306159",
        "title": "Terra formars. Vol. 1",
        "author": "Yu Sasuga, Ken'ichi Tachibana",
        "publisher": "Kazé",
        "published": "2013-01-30",
        "year": 2013,
        "format": "Poche",
        "genre": "Mangas",
        "pages": null,
        "read": false,
        "rating": 0,
        "comment": "",
        "gleeph_url": "https://www.gleeph.com/book/ean/9782820306159",
        "image": "books-cover/9782820306159.jpg",
        "date_added": "2026-07-17T13:30:46.644Z"
    },
    {
        "isbn": "9782413003526",
        "title": "Sillage : premières armes. Vol. 2. Vitesse de croisière",
        "author": "Jean-David Morvan, Philippe Buchet, Pierre-Mony Chan",
        "publisher": "Delcourt",
        "published": "2020-10-07",
        "year": 2020,
        "format": "Grand Format",
        "genre": "Bandes dessinées & Comics",
        "pages": null,
        "read": true,
        "rating": 0,
        "comment": "",
        "gleeph_url": "https://www.gleeph.com/book/ean/9782413003526",
        "image": "books-cover/9782413003526.jpg",
        "date_added": "2026-07-17T13:29:29.622Z"
    },
    {
        "isbn": "9782413080855",
        "title": "Sillage : l'intégrale. Vol. 7. Tome 19 à 21",
        "author": "Jean-David Morvan, Philippe Buchet",
        "publisher": "Delcourt",
        "published": "2023-10-11",
        "year": 2023,
        "format": "Grand Format",
        "genre": "Bandes dessinées & Comics",
        "pages": null,
        "read": true,
        "rating": 0,
        "comment": "",
        "gleeph_url": "https://www.gleeph.com/book/ean/9782413080855",
        "image": "books-cover/9782413080855.jpg",
        "date_added": "2026-07-17T13:29:29.622Z"
    },
    {
        "isbn": "9782756020563",
        "title": "Sillage : l'intégrale. Tomes 1 à 3",
        "author": "Jean-David Morvan, Philippe Buchet",
        "publisher": "Delcourt",
        "published": "2009-11-25",
        "year": 2009,
        "format": "Grand Format",
        "genre": "Bandes dessinées & Comics",
        "pages": null,
        "read": true,
        "rating": 0,
        "comment": "",
        "gleeph_url": "https://www.gleeph.com/book/ean/9782756020563",
        "image": "books-cover/9782756020563.jpg",
        "date_added": "2026-07-17T13:29:29.622Z"
    },
    {
        "isbn": "9782756023878",
        "title": "Sillage : l'intégrale. Tomes 4 à 6",
        "author": "Jean-David Morvan, Philippe Buchet",
        "publisher": "Delcourt",
        "published": "2010-11-17",
        "year": 2010,
        "format": "Grand Format",
        "genre": "Bandes dessinées & Comics",
        "pages": null,
        "read": true,
        "rating": 0,
        "comment": "",
        "gleeph_url": "https://www.gleeph.com/book/ean/9782756023878",
        "image": "books-cover/9782756023878.jpg",
        "date_added": "2026-07-17T13:29:29.622Z"
    },
    {
        "isbn": "9782756026497",
        "title": "Sillage : l'intégrale. Tomes 7 à 9",
        "author": "Jean-David Morvan, Philippe Buchet",
        "publisher": "Delcourt",
        "published": "2011-11-02",
        "year": 2011,
        "format": "Grand Format",
        "genre": "Bandes dessinées & Comics",
        "pages": null,
        "read": true,
        "rating": 0,
        "comment": "",
        "gleeph_url": "https://www.gleeph.com/book/ean/9782756026497",
        "image": "books-cover/9782756026497.jpg",
        "date_added": "2026-07-17T13:29:29.622Z"
    },
    {
        "isbn": "9782756027319",
        "title": "Sillage : l'intégrale. Tomes 10 à 12",
        "author": "Jean-David Morvan, Philippe Buchet",
        "publisher": "Delcourt",
        "published": "2011-11-02",
        "year": 2011,
        "format": "Grand Format",
        "genre": "Bandes dessinées & Comics",
        "pages": null,
        "read": true,
        "rating": 0,
        "comment": "",
        "gleeph_url": "https://www.gleeph.com/book/ean/9782756027319",
        "image": "books-cover/9782756027319.jpg",
        "date_added": "2026-07-17T13:29:29.622Z"
    },
    {
        "isbn": "9782756038933",
        "title": "Sillage : premières armes. Vol. 1. Esprit d'équipe",
        "author": "Jean-David Morvan, Philippe Buchet, Pierre-Mony Chan",
        "publisher": "Delcourt",
        "published": "2014-06-11",
        "year": 2014,
        "format": "Grand Format",
        "genre": "Bandes dessinées & Comics",
        "pages": null,
        "read": true,
        "rating": 0,
        "comment": "",
        "gleeph_url": "https://www.gleeph.com/book/ean/9782756038933",
        "image": "books-cover/9782756038933.jpg",
        "date_added": "2026-07-17T13:29:29.622Z"
    },
    {
        "isbn": "9782756040530",
        "title": "Sillage : l'intégrale. Tomes 13 à 15",
        "author": "Jean-David Morvan, Philippe Buchet",
        "publisher": "Delcourt",
        "published": "2013-09-25",
        "year": 2013,
        "format": "Grand Format",
        "genre": "Bandes dessinées & Comics",
        "pages": null,
        "read": true,
        "rating": 0,
        "comment": "",
        "gleeph_url": "https://www.gleeph.com/book/ean/9782756040530",
        "image": "books-cover/9782756040530.jpg",
        "date_added": "2026-07-17T13:29:29.622Z"
    },
    {
        "isbn": "9782756082080",
        "title": "Sillage : l'intégrale. Tomes 16 à 18",
        "author": "Jean-David Morvan, Philippe Buchet",
        "publisher": "Delcourt",
        "published": "2016-10-12",
        "year": 2016,
        "format": "Grand Format",
        "genre": "Bandes dessinées & Comics",
        "pages": null,
        "read": true,
        "rating": 0,
        "comment": "",
        "gleeph_url": "https://www.gleeph.com/book/ean/9782756082080",
        "image": "books-cover/9782756082080.jpg",
        "date_added": "2026-07-17T13:29:29.622Z"
    },
    {
        "isbn": "9791032405123",
        "title": "Le dernier jour de Howard Phillips Lovecraft",
        "author": "Romuald Giulivo, Jakub Rebelka",
        "publisher": "Editions 404",
        "published": "2023-10-26",
        "year": 2023,
        "format": "Grand Format",
        "genre": "Bandes dessinées & Comics",
        "pages": null,
        "read": false,
        "rating": 0,
        "comment": "",
        "gleeph_url": "https://www.gleeph.com/book/ean/9791032405123",
        "image": "books-cover/9791032405123.jpg",
        "date_added": "2026-07-17T13:27:21.835Z"
    },
    {
        "isbn": "9780786967476",
        "title": "D&D Player's Handbook",
        "author": "Richard Baker, Jeremy Crawford, Bruce R. Cordell, James Wyatt, Robert J. Schwalb",
        "publisher": "Wizards of the coast",
        "published": "2021-08-10",
        "year": 2021,
        "format": "Unknown",
        "genre": "Bien-être, Loisirs & Vie pratique",
        "pages": null,
        "read": true,
        "rating": 0,
        "comment": "",
        "gleeph_url": "https://www.gleeph.com/book/ean/9780786967476",
        "image": "books-cover/9780786967476.jpg",
        "date_added": "2026-07-17T13:26:52.804Z"
    },
    {
        "isbn": "9781847329011",
        "title": "The Sherlock Holmes Puzzle Collection",
        "author": "John Watson",
        "publisher": "Carlton",
        "published": "2011-10-20",
        "year": 2011,
        "format": "Grand Format",
        "genre": "Autres",
        "pages": null,
        "read": true,
        "rating": 0,
        "comment": "",
        "gleeph_url": "https://www.gleeph.com/book/ean/9781847329011",
        "image": "books-cover/9781847329011.jpg",
        "date_added": "2026-07-17T13:26:52.804Z"
    },
    {
        "isbn": "9782756035734",
        "title": "Les Indes fourbes ou Une seconde partie de l'histoire de la vie de l'aventurier nommé Don Pablos de Ségovie, vagabond exemplaire et miroir des filous...",
        "author": "Alain Ayroles, Juanjo Guarnido",
        "publisher": "Delcourt",
        "published": "2019-08-28",
        "year": 2019,
        "format": "Grand Format",
        "genre": "Bandes dessinées & Comics",
        "pages": null,
        "read": true,
        "rating": 0,
        "comment": "",
        "gleeph_url": "https://www.gleeph.com/book/ean/9782756035734",
        "image": "books-cover/9782756035734.jpg",
        "date_added": "2026-07-17T13:26:52.804Z"
    },
    {
        "isbn": "9782203153622",
        "title": "Gloutons & dragons. Vol. 4",
        "author": "Ryoko Kui",
        "publisher": "Casterman",
        "published": "2018-02-14",
        "year": 2018,
        "format": "Poche",
        "genre": "Mangas",
        "pages": null,
        "read": true,
        "rating": 0,
        "comment": "",
        "gleeph_url": "https://www.gleeph.com/book/ean/9782203153622",
        "image": "books-cover/9782203153622.jpg",
        "date_added": "2023-05-08T07:05:09.189Z"
    },
    {
        "isbn": "9782203161238",
        "title": "Gloutons & dragons. Vol. 3",
        "author": "Ryoko Kui",
        "publisher": "Casterman",
        "published": "2017-10-11",
        "year": 2017,
        "format": "E-book",
        "genre": "Mangas",
        "pages": null,
        "read": true,
        "rating": 0,
        "comment": "",
        "gleeph_url": "https://www.gleeph.com/book/ean/9782203161238",
        "image": "books-cover/9782203161238.jpg",
        "date_added": "2023-05-08T07:05:16.550Z"
    },
    {
        "isbn": "9782203121621",
        "title": "Gloutons & dragons. Vol. 2",
        "author": "Ryoko Kui",
        "publisher": "Casterman",
        "published": "2017-08-23",
        "year": 2017,
        "format": "Poche",
        "genre": "Mangas",
        "pages": null,
        "read": true,
        "rating": 0,
        "comment": "",
        "gleeph_url": "https://www.gleeph.com/book/ean/9782203121621",
        "image": "books-cover/9782203121621.jpg",
        "date_added": "2023-05-08T10:53:53.180Z"
    },
    {
        "isbn": "9782810202294",
        "title": "Hoka Hey!",
        "author": "Neyef",
        "publisher": "Rue de Sèvres",
        "published": "2022-10-26",
        "year": 2022,
        "format": "Grand Format",
        "genre": "Bandes dessinées & Comics",
        "pages": null,
        "read": true,
        "rating": 0,
        "comment": "",
        "gleeph_url": "https://www.gleeph.com/book/ean/9782810202294",
        "image": "books-cover/9782810202294.jpg",
        "date_added": "2023-05-13T06:45:04.512Z"
    },
    {
        "isbn": "9791036362842",
        "title": "Murtagh",
        "author": "Christopher Paolini",
        "publisher": "Bayard Jeunesse",
        "published": "2023-11-08",
        "year": 2023,
        "format": "Grand Format",
        "genre": "Jeunesse",
        "pages": 746,
        "read": false,
        "rating": 0,
        "comment": "",
        "gleeph_url": "https://www.gleeph.com/book/ean/9791036362842",
        "image": "books-cover/9791036362842.jpg",
        "date_added": "2026-07-17T12:45:15.001Z"
    },
    {
        "isbn": "9782253253198",
        "title": "Papi Mariole",
        "author": "Benoît Philippon",
        "publisher": "Le Livre de poche",
        "published": "2025-02-19",
        "year": 2025,
        "format": "Poche",
        "genre": "Policiers & Thrillers",
        "pages": null,
        "read": true,
        "rating": 4,
        "comment": "",
        "gleeph_url": "https://www.gleeph.com/book/ean/9782253253198",
        "image": "books-cover/9782253253198.jpg",
        "date_added": "2026-07-17T08:17:01.251Z"
    },
    {
        "isbn": "9782203228610",
        "title": "Meurtre mode d'emploi. Vol. 1. Présumée innocente",
        "author": "Holly Jackson",
        "publisher": "Casterman",
        "published": "2021-09-08",
        "year": 2021,
        "format": "Grand Format",
        "genre": "Jeunes adultes",
        "pages": null,
        "read": false,
        "rating": 0,
        "comment": "",
        "gleeph_url": "https://www.gleeph.com/book/ean/9782203228610",
        "image": "books-cover/9782203228610.jpg",
        "date_added": "2026-07-17T08:17:01.251Z"
    },
    {
        "isbn": "9782810208784",
        "title": "Le château des étoiles : intégrale tomes 1 & 2",
        "author": "Alex Alice",
        "publisher": "Rue de Sèvres",
        "published": "2024-09-18",
        "year": 2024,
        "format": "Grand Format",
        "genre": "Bandes dessinées & Comics",
        "pages": null,
        "read": false,
        "rating": 0,
        "comment": "",
        "gleeph_url": "https://www.gleeph.com/book/ean/9782810208784",
        "image": "books-cover/9782810208784.jpg",
        "date_added": "2026-07-17T08:17:01.251Z"
    },
    {
        "isbn": "9782290407981",
        "title": "La neige ne tombe pas en hiver",
        "author": "Bruno Combes",
        "publisher": "J'ai lu",
        "published": "2025-05-07",
        "year": 2025,
        "format": "Poche",
        "genre": "Romans & Nouvelles",
        "pages": null,
        "read": false,
        "rating": 0,
        "comment": "",
        "gleeph_url": "https://www.gleeph.com/book/ean/9782290407981",
        "image": "books-cover/9782290407981.jpg",
        "date_added": "2026-07-17T08:17:01.251Z"
    },
    {
        "isbn": "9782266351546",
        "title": "Les soleils mouillés",
        "author": "Françoise Bourdin",
        "publisher": "Pocket",
        "published": "2026-03-05",
        "year": 2026,
        "format": "Poche",
        "genre": "Romans & Nouvelles",
        "pages": null,
        "read": true,
        "rating": 3,
        "comment": "",
        "gleeph_url": "https://www.gleeph.com/book/ean/9782266351546",
        "image": "books-cover/9782266351546.jpg",
        "date_added": "2026-07-11T12:16:49.592Z"
    },
    {
        "isbn": "9782253256731",
        "title": "La chambre des merveilles",
        "author": "Julien Sandrel",
        "publisher": "Le Livre de poche",
        "published": "2025-10-29",
        "year": 2025,
        "format": "Poche",
        "genre": "Romans & Nouvelles",
        "pages": null,
        "read": true,
        "rating": 5,
        "comment": "",
        "gleeph_url": "https://www.gleeph.com/book/ean/9782253256731",
        "image": "books-cover/9782253256731.jpg",
        "date_added": "2026-07-11T12:15:02.949Z"
    },
    {
        "isbn": "9782253255079",
        "title": "Holly",
        "author": "Stephen King",
        "publisher": "Le Livre de poche",
        "published": "2026-01-28",
        "year": 2026,
        "format": "Poche",
        "genre": "Imaginaire",
        "pages": null,
        "read": true,
        "rating": 4,
        "comment": "",
        "gleeph_url": "https://www.gleeph.com/book/ean/9782253255079",
        "image": "books-cover/9782253255079.jpg",
        "date_added": "2026-07-11T12:13:34.750Z"
    },
    {
        "isbn": "9791028111717",
        "title": "Le sorceleur. Vol. 3. Le sang des elfes",
        "author": "Andrzej Sapkowski",
        "publisher": "Bragelonne",
        "published": "2019-05-15",
        "year": 2019,
        "format": "Grand Format",
        "genre": "Imaginaire",
        "pages": null,
        "read": false,
        "rating": 0,
        "comment": "",
        "gleeph_url": "https://www.gleeph.com/book/ean/9791028111717",
        "image": "books-cover/9791028111717.jpg",
        "date_added": "2023-05-14T17:54:25.839Z"
    },
    {
        "isbn": "9782871292562",
        "title": "Yu-Gi-Oh !. Vol. 12",
        "author": "Kazuki Takahashi",
        "publisher": "Kana",
        "published": "+032850-11",
        "year": 32850,
        "format": "Poche",
        "genre": "Mangas",
        "pages": null,
        "read": true,
        "rating": 0,
        "comment": "",
        "gleeph_url": "https://www.gleeph.com/book/ean/9782871292562",
        "image": "books-cover/9782871292562.jpg",
        "date_added": "2024-03-16T09:51:26.760Z"
    },
    {
        "isbn": "9782871292555",
        "title": "Yu-Gi-Oh !. Vol. 11",
        "author": "Kazuki Takahashi",
        "publisher": "Kana",
        "published": "+032678-05",
        "year": 32678,
        "format": "Poche",
        "genre": "Mangas",
        "pages": null,
        "read": true,
        "rating": 0,
        "comment": "",
        "gleeph_url": "https://www.gleeph.com/book/ean/9782871292555",
        "image": "books-cover/9782871292555.jpg",
        "date_added": "2024-03-16T09:51:26.760Z"
    },
    {
        "isbn": "9782756402321",
        "title": "Les rois-dragons. Vol. 1. Le Palais adamantin",
        "author": "Stephen Deas",
        "publisher": "Pygmalion",
        "published": "2009-06-17",
        "year": 2009,
        "format": "Grand Format",
        "genre": "Imaginaire",
        "pages": null,
        "read": false,
        "rating": 0,
        "comment": "",
        "gleeph_url": "https://www.gleeph.com/book/ean/9782756402321",
        "image": "books-cover/9782756402321.jpg",
        "date_added": "2024-03-16T09:53:25.237Z"
    },
    {
        "isbn": "9782871292241",
        "title": "Yu-Gi-Oh !. Vol. 2",
        "author": "Kazuki Takahashi",
        "publisher": "Kana",
        "published": "2001-12-07",
        "year": 2001,
        "format": "Poche",
        "genre": "Mangas",
        "pages": null,
        "read": true,
        "rating": 0,
        "comment": "",
        "gleeph_url": "https://www.gleeph.com/book/ean/9782871292241",
        "image": "books-cover/9782871292241.jpg",
        "date_added": "2024-03-16T09:51:26.760Z"
    },
    {
        "isbn": "9782871292258",
        "title": "Yu-Gi-Oh !. Vol. 3",
        "author": "Kazuki Takahashi",
        "publisher": "Kana",
        "published": "2001-12-07",
        "year": 2001,
        "format": "Poche",
        "genre": "Mangas",
        "pages": null,
        "read": true,
        "rating": 0,
        "comment": "",
        "gleeph_url": "https://www.gleeph.com/book/ean/9782871292258",
        "image": "books-cover/9782871292258.jpg",
        "date_added": "2024-03-16T09:51:26.760Z"
    },
    {
        "isbn": "9782871292265",
        "title": "Yu-Gi-Oh !. Vol. 4",
        "author": "Kazuki Takahashi",
        "publisher": "Kana",
        "published": "2001-12-07",
        "year": 2001,
        "format": "Poche",
        "genre": "Mangas",
        "pages": null,
        "read": true,
        "rating": 0,
        "comment": "",
        "gleeph_url": "https://www.gleeph.com/book/ean/9782871292265",
        "image": "books-cover/9782871292265.jpg",
        "date_added": "2024-03-16T09:51:26.760Z"
    },
    {
        "isbn": "9782871292272",
        "title": "Yu-Gi-Oh !. Vol. 5",
        "author": "Kazuki Takahashi",
        "publisher": "Kana",
        "published": "+031303-12",
        "year": 31303,
        "format": "Poche",
        "genre": "Mangas",
        "pages": null,
        "read": true,
        "rating": 0,
        "comment": "",
        "gleeph_url": "https://www.gleeph.com/book/ean/9782871292272",
        "image": "books-cover/9782871292272.jpg",
        "date_added": "2024-03-16T09:51:26.760Z"
    },
    {
        "isbn": "9782871292289",
        "title": "Yu-Gi-Oh !. Vol. 6",
        "author": "Kazuki Takahashi",
        "publisher": "Kana",
        "published": "+031539-05",
        "year": 31539,
        "format": "Poche",
        "genre": "Mangas",
        "pages": null,
        "read": true,
        "rating": 0,
        "comment": "",
        "gleeph_url": "https://www.gleeph.com/book/ean/9782871292289",
        "image": "books-cover/9782871292289.jpg",
        "date_added": "2024-03-16T09:51:26.760Z"
    },
    {
        "isbn": "9782871292517",
        "title": "Yu-Gi-Oh !. Vol. 7",
        "author": "Kazuki Takahashi",
        "publisher": "Kana",
        "published": "+032007-07",
        "year": 32007,
        "format": "Poche",
        "genre": "Mangas",
        "pages": null,
        "read": true,
        "rating": 0,
        "comment": "",
        "gleeph_url": "https://www.gleeph.com/book/ean/9782871292517",
        "image": "books-cover/9782871292517.jpg",
        "date_added": "2024-03-16T09:51:26.760Z"
    },
    {
        "isbn": "9782871292524",
        "title": "Yu-Gi-Oh !. Vol. 8",
        "author": "Kazuki Takahashi",
        "publisher": "Kana",
        "published": "2002-11-21",
        "year": 2002,
        "format": "Poche",
        "genre": "Mangas",
        "pages": null,
        "read": true,
        "rating": 0,
        "comment": "",
        "gleeph_url": "https://www.gleeph.com/book/ean/9782871292524",
        "image": "books-cover/9782871292524.jpg",
        "date_added": "2024-03-16T09:51:26.760Z"
    },
    {
        "isbn": "9782871292531",
        "title": "Yu-Gi-Oh !. Vol. 9",
        "author": "Kazuki Takahashi",
        "publisher": "Kana",
        "published": "+032218-05",
        "year": 32218,
        "format": "Poche",
        "genre": "Mangas",
        "pages": null,
        "read": true,
        "rating": 0,
        "comment": "",
        "gleeph_url": "https://www.gleeph.com/book/ean/9782871292531",
        "image": "books-cover/9782871292531.jpg",
        "date_added": "2024-03-16T09:51:26.760Z"
    },
    {
        "isbn": "9782871292548",
        "title": "Yu-Gi-Oh !. Vol. 10",
        "author": "Kazuki Takahashi",
        "publisher": "Kana",
        "published": "+032429-03",
        "year": 32429,
        "format": "Poche",
        "genre": "Mangas",
        "pages": null,
        "read": true,
        "rating": 0,
        "comment": "",
        "gleeph_url": "https://www.gleeph.com/book/ean/9782871292548",
        "image": "books-cover/9782871292548.jpg",
        "date_added": "2024-03-16T09:51:26.760Z"
    },
    {
        "isbn": "9782871293316",
        "title": "Yu-Gi-Oh !. Vol. 13",
        "author": "Kazuki Takahashi",
        "publisher": "Kana",
        "published": "+033004-03",
        "year": 33004,
        "format": "Poche",
        "genre": "Mangas",
        "pages": null,
        "read": false,
        "rating": 0,
        "comment": "",
        "gleeph_url": "https://www.gleeph.com/book/ean/9782871293316",
        "image": "books-cover/9782871293316.jpg",
        "date_added": "2024-03-16T09:51:26.760Z"
    },
    {
        "isbn": "9782871293323",
        "title": "Yu-Gi-Oh !. Vol. 14",
        "author": "Kazuki Takahashi",
        "publisher": "Kana",
        "published": "+033138-05",
        "year": 33138,
        "format": "Poche",
        "genre": "Mangas",
        "pages": null,
        "read": false,
        "rating": 0,
        "comment": "",
        "gleeph_url": "https://www.gleeph.com/book/ean/9782871293323",
        "image": "books-cover/9782871293323.jpg",
        "date_added": "2024-03-16T09:51:26.760Z"
    },
    {
        "isbn": "9782871293330",
        "title": "Yu-Gi-Oh !. Vol. 15",
        "author": "Kazuki Takahashi",
        "publisher": "Kana",
        "published": "+033387-06",
        "year": 33387,
        "format": "Poche",
        "genre": "Mangas",
        "pages": null,
        "read": false,
        "rating": 0,
        "comment": "",
        "gleeph_url": "https://www.gleeph.com/book/ean/9782871293330",
        "image": "books-cover/9782871293330.jpg",
        "date_added": "2024-03-16T09:51:26.760Z"
    },
    {
        "isbn": "9782871293347",
        "title": "Yu-Gi-Oh !. Vol. 16",
        "author": "Kazuki Takahashi",
        "publisher": "Kana",
        "published": "+033655-10",
        "year": 33655,
        "format": "Poche",
        "genre": "Mangas",
        "pages": null,
        "read": false,
        "rating": 0,
        "comment": "",
        "gleeph_url": "https://www.gleeph.com/book/ean/9782871293347",
        "image": "books-cover/9782871293347.jpg",
        "date_added": "2024-03-16T09:51:26.760Z"
    },
    {
        "isbn": "9782871293354",
        "title": "Yu-Gi-Oh !. Vol. 17",
        "author": "Kazuki Takahashi",
        "publisher": "Kana",
        "published": "2001-12-04",
        "year": 2001,
        "format": "Poche",
        "genre": "Mangas",
        "pages": null,
        "read": false,
        "rating": 0,
        "comment": "",
        "gleeph_url": "https://www.gleeph.com/book/ean/9782871293354",
        "image": "books-cover/9782871293354.jpg",
        "date_added": "2024-03-16T09:51:26.760Z"
    },
    {
        "isbn": "9782871294078",
        "title": "Yu-Gi-Oh !. Vol. 18",
        "author": "Kazuki Takahashi",
        "publisher": "Kana",
        "published": "2003-01-30",
        "year": 2003,
        "format": "Poche",
        "genre": "Mangas",
        "pages": null,
        "read": false,
        "rating": 0,
        "comment": "",
        "gleeph_url": "https://www.gleeph.com/book/ean/9782871294078",
        "image": "books-cover/9782871294078.jpg",
        "date_added": "2024-03-16T09:51:26.760Z"
    },
    {
        "isbn": "9782871294238",
        "title": "Yu-Gi-Oh !. Vol. 19",
        "author": "Kazuki Takahashi",
        "publisher": "Kana",
        "published": "2002-06-02",
        "year": 2002,
        "format": "Poche",
        "genre": "Mangas",
        "pages": null,
        "read": false,
        "rating": 0,
        "comment": "",
        "gleeph_url": "https://www.gleeph.com/book/ean/9782871294238",
        "image": "books-cover/9782871294238.jpg",
        "date_added": "2024-03-16T09:51:26.760Z"
    },
    {
        "isbn": "9782871294368",
        "title": "Yu-Gi-Oh !. Vol. 20",
        "author": "Kazuki Takahashi",
        "publisher": "Kana",
        "published": "2002-10-19",
        "year": 2002,
        "format": "Poche",
        "genre": "Mangas",
        "pages": null,
        "read": false,
        "rating": 0,
        "comment": "",
        "gleeph_url": "https://www.gleeph.com/book/ean/9782871294368",
        "image": "books-cover/9782871294368.jpg",
        "date_added": "2024-03-16T09:51:26.760Z"
    },
    {
        "isbn": "9782871294498",
        "title": "Yu-Gi-Oh !. Vol. 21",
        "author": "Kazuki Takahashi",
        "publisher": "Kana",
        "published": "2002-12-07",
        "year": 2002,
        "format": "Poche",
        "genre": "Mangas",
        "pages": null,
        "read": false,
        "rating": 0,
        "comment": "",
        "gleeph_url": "https://www.gleeph.com/book/ean/9782871294498",
        "image": "books-cover/9782871294498.jpg",
        "date_added": "2024-03-16T09:51:26.760Z"
    },
    {
        "isbn": "9782871294962",
        "title": "Yu-Gi-Oh !. Vol. 22",
        "author": "Kazuki Takahashi",
        "publisher": "Kana",
        "published": "2003-02-03",
        "year": 2003,
        "format": "Poche",
        "genre": "Mangas",
        "pages": null,
        "read": false,
        "rating": 0,
        "comment": "",
        "gleeph_url": "https://www.gleeph.com/book/ean/9782871294962",
        "image": "books-cover/9782871294962.jpg",
        "date_added": "2024-03-16T09:51:26.760Z"
    },
    {
        "isbn": "9782871295150",
        "title": "Yu-Gi-Oh !. Vol. 23",
        "author": "Kazuki Takahashi",
        "publisher": "Kana",
        "published": "2003-06-02",
        "year": 2003,
        "format": "Poche",
        "genre": "Mangas",
        "pages": null,
        "read": false,
        "rating": 0,
        "comment": "",
        "gleeph_url": "https://www.gleeph.com/book/ean/9782871295150",
        "image": "books-cover/9782871295150.jpg",
        "date_added": "2024-03-16T09:51:26.760Z"
    },
    {
        "isbn": "9782871295259",
        "title": "Yu-Gi-Oh !. Vol. 24",
        "author": "Kazuki Takahashi",
        "publisher": "Kana",
        "published": "2003-06-07",
        "year": 2003,
        "format": "Poche",
        "genre": "Mangas",
        "pages": null,
        "read": false,
        "rating": 0,
        "comment": "",
        "gleeph_url": "https://www.gleeph.com/book/ean/9782871295259",
        "image": "books-cover/9782871295259.jpg",
        "date_added": "2024-03-16T09:51:26.760Z"
    },
    {
        "isbn": "9782871295457",
        "title": "Yu-Gi-Oh !. Vol. 25",
        "author": "Kazuki Takahashi",
        "publisher": "Kana",
        "published": "2003-09-05",
        "year": 2003,
        "format": "Poche",
        "genre": "Mangas",
        "pages": null,
        "read": false,
        "rating": 0,
        "comment": "",
        "gleeph_url": "https://www.gleeph.com/book/ean/9782871295457",
        "image": "books-cover/9782871295457.jpg",
        "date_added": "2024-03-16T09:51:26.760Z"
    },
    {
        "isbn": "9782871295587",
        "title": "Yu-Gi-Oh !. Vol. 26",
        "author": "Kazuki Takahashi",
        "publisher": "Kana",
        "published": "2003-10-31",
        "year": 2003,
        "format": "Poche",
        "genre": "Mangas",
        "pages": null,
        "read": false,
        "rating": 0,
        "comment": "",
        "gleeph_url": "https://www.gleeph.com/book/ean/9782871295587",
        "image": "books-cover/9782871295587.jpg",
        "date_added": "2024-03-16T09:51:26.760Z"
    },
    {
        "isbn": "9782871296072",
        "title": "Yu-Gi-Oh !. Vol. 27",
        "author": "Kazuki Takahashi",
        "publisher": "Kana",
        "published": "2004-02-07",
        "year": 2004,
        "format": "Poche",
        "genre": "Mangas",
        "pages": null,
        "read": false,
        "rating": 0,
        "comment": "",
        "gleeph_url": "https://www.gleeph.com/book/ean/9782871296072",
        "image": "books-cover/9782871296072.jpg",
        "date_added": "2024-03-16T09:51:26.760Z"
    },
    {
        "isbn": "9782871296195",
        "title": "Yu-Gi-Oh !. Vol. 28",
        "author": "Kazuki Takahashi",
        "publisher": "Kana",
        "published": "2004-04-01",
        "year": 2004,
        "format": "Poche",
        "genre": "Mangas",
        "pages": null,
        "read": false,
        "rating": 0,
        "comment": "",
        "gleeph_url": "https://www.gleeph.com/book/ean/9782871296195",
        "image": "books-cover/9782871296195.jpg",
        "date_added": "2024-03-16T09:51:26.760Z"
    },
    {
        "isbn": "9782871296300",
        "title": "Yu-Gi-Oh !. Vol. 29",
        "author": "Kazuki Takahashi",
        "publisher": "Kana",
        "published": "2004-06-01",
        "year": 2004,
        "format": "Poche",
        "genre": "Mangas",
        "pages": null,
        "read": false,
        "rating": 0,
        "comment": "",
        "gleeph_url": "https://www.gleeph.com/book/ean/9782871296300",
        "image": "books-cover/9782871296300.jpg",
        "date_added": "2024-03-16T09:51:26.760Z"
    },
    {
        "isbn": "9782871296409",
        "title": "Yu-Gi-Oh !. Vol. 30",
        "author": "Kazuki Takahashi",
        "publisher": "Kana",
        "published": "2004-09-01",
        "year": 2004,
        "format": "Poche",
        "genre": "Mangas",
        "pages": null,
        "read": false,
        "rating": 0,
        "comment": "",
        "gleeph_url": "https://www.gleeph.com/book/ean/9782871296409",
        "image": "books-cover/9782871296409.jpg",
        "date_added": "2024-03-16T09:51:26.760Z"
    },
    {
        "isbn": "9782871296539",
        "title": "Yu-Gi-Oh !. Vol. 31",
        "author": "Kazuki Takahashi",
        "publisher": "Kana",
        "published": "2004-10-01",
        "year": 2004,
        "format": "Poche",
        "genre": "Mangas",
        "pages": null,
        "read": false,
        "rating": 0,
        "comment": "",
        "gleeph_url": "https://www.gleeph.com/book/ean/9782871296539",
        "image": "books-cover/9782871296539.jpg",
        "date_added": "2024-03-16T09:51:26.760Z"
    },
    {
        "isbn": "9782871296638",
        "title": "Yu-Gi-Oh !. Vol. 32",
        "author": "Kazuki Takahashi",
        "publisher": "Kana",
        "published": "2004-12-04",
        "year": 2004,
        "format": "Poche",
        "genre": "Mangas",
        "pages": null,
        "read": false,
        "rating": 0,
        "comment": "",
        "gleeph_url": "https://www.gleeph.com/book/ean/9782871296638",
        "image": "books-cover/9782871296638.jpg",
        "date_added": "2024-03-16T09:51:26.760Z"
    },
    {
        "isbn": "9782871297130",
        "title": "Yu-Gi-Oh !. Vol. 33",
        "author": "Kazuki Takahashi",
        "publisher": "Kana",
        "published": "2005-02-04",
        "year": 2005,
        "format": "Poche",
        "genre": "Mangas",
        "pages": null,
        "read": false,
        "rating": 0,
        "comment": "",
        "gleeph_url": "https://www.gleeph.com/book/ean/9782871297130",
        "image": "books-cover/9782871297130.jpg",
        "date_added": "2024-03-16T09:51:26.760Z"
    },
    {
        "isbn": "9782871297666",
        "title": "Yu-Gi-Oh !. Vol. 34",
        "author": "Kazuki Takahashi",
        "publisher": "Kana",
        "published": "2005-04-02",
        "year": 2005,
        "format": "Poche",
        "genre": "Mangas",
        "pages": null,
        "read": false,
        "rating": 0,
        "comment": "",
        "gleeph_url": "https://www.gleeph.com/book/ean/9782871297666",
        "image": "books-cover/9782871297666.jpg",
        "date_added": "2024-03-16T09:51:26.760Z"
    },
    {
        "isbn": "9782871297871",
        "title": "Yu-Gi-Oh !. Vol. 35",
        "author": "Kazuki Takahashi",
        "publisher": "Kana",
        "published": "2005-06-30",
        "year": 2005,
        "format": "Poche",
        "genre": "Mangas",
        "pages": null,
        "read": false,
        "rating": 0,
        "comment": "",
        "gleeph_url": "https://www.gleeph.com/book/ean/9782871297871",
        "image": "books-cover/9782871297871.jpg",
        "date_added": "2024-03-16T09:51:26.760Z"
    },
    {
        "isbn": "9782871298076",
        "title": "Yu-Gi-Oh !. Vol. 36",
        "author": "Kazuki Takahashi",
        "publisher": "Kana",
        "published": "2005-08-25",
        "year": 2005,
        "format": "Poche",
        "genre": "Mangas",
        "pages": null,
        "read": false,
        "rating": 0,
        "comment": "",
        "gleeph_url": "https://www.gleeph.com/book/ean/9782871298076",
        "image": "books-cover/9782871298076.jpg",
        "date_added": "2024-03-16T09:51:26.760Z"
    },
    {
        "isbn": "9782871298250",
        "title": "Yu-Gi-Oh !. Vol. 37",
        "author": "Kazuki Takahashi",
        "publisher": "Kana",
        "published": "2005-10-07",
        "year": 2005,
        "format": "Poche",
        "genre": "Mangas",
        "pages": null,
        "read": false,
        "rating": 0,
        "comment": "",
        "gleeph_url": "https://www.gleeph.com/book/ean/9782871298250",
        "image": "books-cover/9782871298250.jpg",
        "date_added": "2024-03-16T09:51:26.760Z"
    },
    {
        "isbn": "9782871298441",
        "title": "Yu-Gi-Oh !. Vol. 38",
        "author": "Kazuki Takahashi",
        "publisher": "Kana",
        "published": "2005-12-01",
        "year": 2005,
        "format": "Poche",
        "genre": "Mangas",
        "pages": null,
        "read": false,
        "rating": 0,
        "comment": "",
        "gleeph_url": "https://www.gleeph.com/book/ean/9782871298441",
        "image": "books-cover/9782871298441.jpg",
        "date_added": "2024-03-16T09:51:26.760Z"
    },
    {
        "isbn": "9791026825029",
        "title": "The nice house on the lake. Vol. 2",
        "author": "James Tynion, Alvaro Martinez",
        "publisher": "Urban comics",
        "published": "2023-03-31",
        "year": 2023,
        "format": "Grand Format",
        "genre": "Bandes dessinées & Comics",
        "pages": null,
        "read": true,
        "rating": 0,
        "comment": "",
        "gleeph_url": "https://www.gleeph.com/book/ean/9791026825029",
        "image": "books-cover/9791026825029.jpg",
        "date_added": "2024-03-16T09:47:44.640Z"
    },
    {
        "isbn": "9791026827887",
        "title": "The nice house on the lake. Vol. 1",
        "author": "James Tynion, Alvaro Martinez",
        "publisher": "Urban comics",
        "published": "2023-02-03",
        "year": 2023,
        "format": "Grand Format",
        "genre": "Bandes dessinées & Comics",
        "pages": null,
        "read": true,
        "rating": 0,
        "comment": "",
        "gleeph_url": "https://www.gleeph.com/book/ean/9791026827887",
        "image": "books-cover/9791026827887.jpg",
        "date_added": "2024-03-16T09:46:24.111Z"
    },
    {
        "isbn": "9782871292234",
        "title": "Yu-Gi-Oh !. Vol. 1",
        "author": "Kazuki Takahashi",
        "publisher": "Kana",
        "published": "2001-12-07",
        "year": 2001,
        "format": "Poche",
        "genre": "Mangas",
        "pages": null,
        "read": true,
        "rating": 0,
        "comment": "",
        "gleeph_url": "https://www.gleeph.com/book/ean/9782871292234",
        "image": "books-cover/9782871292234.jpg",
        "date_added": "2023-08-09T07:03:11.110Z"
    },
    {
        "isbn": "9782747019248",
        "title": "Ulysse Moore. Vol. 1. Les clefs du temps",
        "author": "Pierdomenico Baccalario",
        "publisher": "Bayard Jeunesse",
        "published": "2006-05-11",
        "year": 2006,
        "format": "Grand Format",
        "genre": "Jeunesse",
        "pages": null,
        "read": true,
        "rating": 0,
        "comment": "",
        "gleeph_url": "https://www.gleeph.com/book/ean/9782747019248",
        "image": "books-cover/9782747019248.jpg",
        "date_added": "2023-05-14T17:41:52.847Z"
    },
    {
        "isbn": "9782747034609",
        "title": "Ulysse Moore. Vol. 8. Le maître de la foudre",
        "author": "Pierdomenico Baccalario",
        "publisher": "Bayard Jeunesse",
        "published": "2011-07-15",
        "year": 2011,
        "format": "Grand Format",
        "genre": "Jeunesse",
        "pages": null,
        "read": true,
        "rating": 0,
        "comment": "",
        "gleeph_url": "https://www.gleeph.com/book/ean/9782747034609",
        "image": "books-cover/9782747034609.jpg",
        "date_added": "2023-05-14T17:40:58.916Z"
    },
    {
        "isbn": "9782747019538",
        "title": "Ulysse Moore. Vol. 2. La boutique des cartes perdues",
        "author": "Pierdomenico Baccalario",
        "publisher": "Bayard Jeunesse",
        "published": "2006-11-09",
        "year": 2006,
        "format": "Grand Format",
        "genre": "Jeunesse",
        "pages": null,
        "read": true,
        "rating": 0,
        "comment": "",
        "gleeph_url": "https://www.gleeph.com/book/ean/9782747019538",
        "image": "books-cover/9782747019538.jpg",
        "date_added": "2023-05-14T17:40:33.955Z"
    },
    {
        "isbn": "9782747019545",
        "title": "Ulysse Moore. Vol. 3. La maison aux miroirs",
        "author": "Pierdomenico Baccalario",
        "publisher": "Bayard Jeunesse",
        "published": "2007-04-20",
        "year": 2007,
        "format": "Grand Format",
        "genre": "Jeunesse",
        "pages": null,
        "read": true,
        "rating": 0,
        "comment": "",
        "gleeph_url": "https://www.gleeph.com/book/ean/9782747019545",
        "image": "books-cover/9782747019545.jpg",
        "date_added": "2023-05-14T17:40:20.715Z"
    },
    {
        "isbn": "9782747024556",
        "title": "Ulysse Moore. Vol. 5. Les gardiens de pierre",
        "author": "Pierdomenico Baccalario",
        "publisher": "Bayard Jeunesse",
        "published": "2008-05-29",
        "year": 2008,
        "format": "Grand Format",
        "genre": "Jeunesse",
        "pages": null,
        "read": true,
        "rating": 0,
        "comment": "",
        "gleeph_url": "https://www.gleeph.com/book/ean/9782747024556",
        "image": "books-cover/9782747024556.jpg",
        "date_added": "2023-05-14T17:39:50.887Z"
    },
    {
        "isbn": "9782747037020",
        "title": "Ulysse Moore. Vol. 9. Le labyrinthe d'ombre",
        "author": "Pierdomenico Baccalario",
        "publisher": "Bayard Jeunesse",
        "published": "2012-02-23",
        "year": 2012,
        "format": "Grand Format",
        "genre": "Jeunesse",
        "pages": null,
        "read": true,
        "rating": 0,
        "comment": "",
        "gleeph_url": "https://www.gleeph.com/book/ean/9782747037020",
        "image": "books-cover/9782747037020.jpg",
        "date_added": "2023-05-14T17:39:18.471Z"
    },
    {
        "isbn": "9782747033985",
        "title": "Ulysse Moore. Vol. 7. La ville cachée",
        "author": "Pierdomenico Baccalario",
        "publisher": "Bayard Jeunesse",
        "published": "2010-11-18",
        "year": 2010,
        "format": "Grand Format",
        "genre": "Jeunesse",
        "pages": null,
        "read": true,
        "rating": 0,
        "comment": "",
        "gleeph_url": "https://www.gleeph.com/book/ean/9782747033985",
        "image": "books-cover/9782747033985.jpg",
        "date_added": "2023-05-14T17:39:01.823Z"
    },
    {
        "isbn": "9782747023801",
        "title": "Ulysse Moore. Vol. 4. L'île aux masques",
        "author": "Pierdomenico Baccalario",
        "publisher": "Bayard Jeunesse",
        "published": "2007-11-08",
        "year": 2007,
        "format": "Grand Format",
        "genre": "Jeunesse",
        "pages": null,
        "read": true,
        "rating": 0,
        "comment": "",
        "gleeph_url": "https://www.gleeph.com/book/ean/9782747023801",
        "image": "books-cover/9782747023801.jpg",
        "date_added": "2023-05-14T17:38:55.020Z"
    },
    {
        "isbn": "9782747024563",
        "title": "Ulysse Moore. Vol. 6. La première clef",
        "author": "Pierdomenico Baccalario",
        "publisher": "Bayard Jeunesse",
        "published": "2008-11-06",
        "year": 2008,
        "format": "Grand Format",
        "genre": "Jeunesse",
        "pages": null,
        "read": true,
        "rating": 0,
        "comment": "",
        "gleeph_url": "https://www.gleeph.com/book/ean/9782747024563",
        "image": "books-cover/9782747024563.jpg",
        "date_added": "2023-05-14T17:38:38.585Z"
    },
    {
        "isbn": "9782266253352",
        "title": "Histoire passionnée de la France",
        "author": "Jean Sévillia",
        "publisher": "Pocket",
        "published": "2015-04-02",
        "year": 2015,
        "format": "Poche",
        "genre": "Art, Culture & Société",
        "pages": null,
        "read": false,
        "rating": 0,
        "comment": "",
        "gleeph_url": "https://www.gleeph.com/book/ean/9782266253352",
        "image": "books-cover/9782266253352.jpg",
        "date_added": "2023-05-13T07:03:26.094Z"
    },
    {
        "isbn": "9782359100112",
        "title": "Freaks' squeele. Vol. 3. Le tango de la mort",
        "author": "Florent Maudoux",
        "publisher": "Ankama",
        "published": "2010-01-28",
        "year": 2010,
        "format": "Grand Format",
        "genre": "Bandes dessinées & Comics",
        "pages": null,
        "read": true,
        "rating": 0,
        "comment": "",
        "gleeph_url": "https://www.gleeph.com/book/ean/9782359100112",
        "image": "books-cover/9782359100112.jpg",
        "date_added": "2023-05-13T06:48:49.976Z"
    },
    {
        "isbn": "9782916739366",
        "title": "Freaks' squeele. Vol. 1. Etrange université",
        "author": "Florent Maudoux",
        "publisher": "Ankama",
        "published": "2008-07-03",
        "year": 2008,
        "format": "Grand Format",
        "genre": "Bandes dessinées & Comics",
        "pages": null,
        "read": true,
        "rating": 0,
        "comment": "",
        "gleeph_url": "https://www.gleeph.com/book/ean/9782916739366",
        "image": "books-cover/9782916739366.jpg",
        "date_added": "2023-05-13T06:48:49.976Z"
    },
    {
        "isbn": "9782916739625",
        "title": "Freaks' squeele. Vol. 2. Les chevaliers qui ne font plus ni !",
        "author": "Florent Maudoux",
        "publisher": "Ankama",
        "published": "2009-03-19",
        "year": 2009,
        "format": "Grand Format",
        "genre": "Bandes dessinées & Comics",
        "pages": null,
        "read": true,
        "rating": 0,
        "comment": "",
        "gleeph_url": "https://www.gleeph.com/book/ean/9782916739625",
        "image": "books-cover/9782916739625.jpg",
        "date_added": "2023-05-13T06:48:49.976Z"
    },
    {
        "isbn": "9782359102628",
        "title": "Freaks' squeele. Vol. 5. Nanorigines",
        "author": "Florent Maudoux",
        "publisher": "Ankama",
        "published": "2012-02-09",
        "year": 2012,
        "format": "Grand Format",
        "genre": "Bandes dessinées & Comics",
        "pages": null,
        "read": false,
        "rating": 0,
        "comment": "",
        "gleeph_url": "https://www.gleeph.com/book/ean/9782359102628",
        "image": "books-cover/9782359102628.jpg",
        "date_added": "2023-05-13T06:48:49.976Z"
    },
    {
        "isbn": "9782359104530",
        "title": "Freaks' squeele. Vol. 6. Clémentine",
        "author": "Florent Maudoux",
        "publisher": "Ankama",
        "published": "2013-09-19",
        "year": 2013,
        "format": "Grand Format",
        "genre": "Bandes dessinées & Comics",
        "pages": null,
        "read": false,
        "rating": 0,
        "comment": "",
        "gleeph_url": "https://www.gleeph.com/book/ean/9782359104530",
        "image": "books-cover/9782359104530.jpg",
        "date_added": "2023-05-13T06:48:49.976Z"
    },
    {
        "isbn": "9782359105278",
        "title": "Freaks' squeele. Vol. 7. A-Move & Z-Movie",
        "author": "",
        "publisher": "Ankama",
        "published": "2015-10-30",
        "year": 2015,
        "format": "Grand Format",
        "genre": "Bandes dessinées & Comics",
        "pages": null,
        "read": false,
        "rating": 0,
        "comment": "",
        "gleeph_url": "https://www.gleeph.com/book/ean/9782359105278",
        "image": "books-cover/9782359105278.jpg",
        "date_added": "2023-05-13T06:48:49.976Z"
    },
    {
        "isbn": "9782302025578",
        "title": "Templier. Vol. 2. Dans la tourmente...",
        "author": "Jean-Luc Istin, Lucio Alberto Leoni, Emanuela Negrin",
        "publisher": "Soleil",
        "published": "2013-06-12",
        "year": 2013,
        "format": "Grand Format",
        "genre": "Bandes dessinées & Comics",
        "pages": null,
        "read": false,
        "rating": 0,
        "comment": "",
        "gleeph_url": "https://www.gleeph.com/book/ean/9782302025578",
        "image": "books-cover/9782302025578.jpg",
        "date_added": "2023-05-13T06:47:00.594Z"
    },
    {
        "isbn": "9782302012394",
        "title": "Templier. Vol. 1. Dans les murailles de Tyr",
        "author": "Jean-Luc Istin, Mirko Colak, Lucio Alberto Leoni",
        "publisher": "Soleil",
        "published": "2012-05-23",
        "year": 2012,
        "format": "Grand Format",
        "genre": "Bandes dessinées & Comics",
        "pages": null,
        "read": false,
        "rating": 0,
        "comment": "",
        "gleeph_url": "https://www.gleeph.com/book/ean/9782302012394",
        "image": "books-cover/9782302012394.jpg",
        "date_added": "2023-05-13T06:46:33.075Z"
    },
    {
        "isbn": "9782203343238",
        "title": "Les cités obscures. Vol. 15. La théorie du grain de sable : 1re partie",
        "author": "François Schuiten, Benoît Peeters",
        "publisher": "Casterman",
        "published": "2007-08-23",
        "year": 2007,
        "format": "Coffret",
        "genre": "Bandes dessinées & Comics",
        "pages": null,
        "read": true,
        "rating": 0,
        "comment": "",
        "gleeph_url": "https://www.gleeph.com/book/ean/9782203343238",
        "image": "books-cover/9782203343238.jpg",
        "date_added": "2023-05-13T06:45:04.512Z"
    },
    {
        "isbn": "9782205057980",
        "title": "Gus. Vol. 1. Nathalie",
        "author": "Christophe Blain",
        "publisher": "Dargaud",
        "published": "2007-01-11",
        "year": 2007,
        "format": "Grand Format",
        "genre": "Bandes dessinées & Comics",
        "pages": null,
        "read": true,
        "rating": 0,
        "comment": "",
        "gleeph_url": "https://www.gleeph.com/book/ean/9782205057980",
        "image": "books-cover/9782205057980.jpg",
        "date_added": "2023-05-13T06:45:04.512Z"
    },
    {
        "isbn": "9782344013328",
        "title": "Ces jours qui disparaissent",
        "author": "Timothé Le Boucher",
        "publisher": "Glénat",
        "published": "2017-09-13",
        "year": 2017,
        "format": "Grand Format",
        "genre": "Bandes dessinées & Comics",
        "pages": null,
        "read": true,
        "rating": 0,
        "comment": "",
        "gleeph_url": "https://www.gleeph.com/book/ean/9782344013328",
        "image": "books-cover/9782344013328.jpg",
        "date_added": "2023-05-13T06:45:04.512Z"
    },
    {
        "isbn": "9782413013518",
        "title": "Penss et les plis du monde",
        "author": "Jérémie Moreau",
        "publisher": "Delcourt",
        "published": "2019-09-25",
        "year": 2019,
        "format": "Grand Format",
        "genre": "Bandes dessinées & Comics",
        "pages": null,
        "read": true,
        "rating": 0,
        "comment": "",
        "gleeph_url": "https://www.gleeph.com/book/ean/9782413013518",
        "image": "books-cover/9782413013518.jpg",
        "date_added": "2023-05-13T06:45:04.512Z"
    },
    {
        "isbn": "9782413029786",
        "title": "Coffret Sillage : premières armes : tomes 1 et 2",
        "author": "Jean-David Morvan, Philippe Buchet, Pierre-Mony Chan",
        "publisher": "Delcourt",
        "published": "2020-10-14",
        "year": 2020,
        "format": "Coffret",
        "genre": "Bandes dessinées & Comics",
        "pages": null,
        "read": true,
        "rating": 0,
        "comment": "",
        "gleeph_url": "https://www.gleeph.com/book/ean/9782413029786",
        "image": "books-cover/9782413029786.jpg",
        "date_added": "2023-05-13T06:45:04.512Z"
    },
    {
        "isbn": "9782413038177",
        "title": "La horde du contrevent. Vol. 3. La Flaque de Lapsane",
        "author": "Eric Henninot",
        "publisher": "Delcourt",
        "published": "2021-10-27",
        "year": 2021,
        "format": "Grand Format",
        "genre": "Bandes dessinées & Comics",
        "pages": null,
        "read": true,
        "rating": 0,
        "comment": "",
        "gleeph_url": "https://www.gleeph.com/book/ean/9782413038177",
        "image": "books-cover/9782413038177.jpg",
        "date_added": "2023-05-13T06:45:04.512Z"
    },
    {
        "isbn": "9782756067261",
        "title": "La horde du contrevent. Vol. 1. Le cosmos est mon campement",
        "author": "Eric Henninot",
        "publisher": "Delcourt",
        "published": "2017-10-18",
        "year": 2017,
        "format": "Grand Format",
        "genre": "Bandes dessinées & Comics",
        "pages": null,
        "read": true,
        "rating": 0,
        "comment": "",
        "gleeph_url": "https://www.gleeph.com/book/ean/9782756067261",
        "image": "books-cover/9782756067261.jpg",
        "date_added": "2023-05-13T06:45:04.512Z"
    },
    {
        "isbn": "9782756072159",
        "title": "La horde du contrevent. Vol. 2. L'escadre frêle",
        "author": "Eric Henninot",
        "publisher": "Delcourt",
        "published": "2019-10-16",
        "year": 2019,
        "format": "Grand Format",
        "genre": "Bandes dessinées & Comics",
        "pages": null,
        "read": true,
        "rating": 0,
        "comment": "",
        "gleeph_url": "https://www.gleeph.com/book/ean/9782756072159",
        "image": "books-cover/9782756072159.jpg",
        "date_added": "2023-05-13T06:45:04.512Z"
    },
    {
        "isbn": "9791028105853",
        "title": "Magic the gathering. La guerre de l'étincelle. Ravnica",
        "author": "Greg Weisman",
        "publisher": "Bragelonne",
        "published": "2019-07-03",
        "year": 2019,
        "format": "Poche",
        "genre": "Jeunesse",
        "pages": null,
        "read": true,
        "rating": 0,
        "comment": "",
        "gleeph_url": "https://www.gleeph.com/book/ean/9791028105853",
        "image": "books-cover/9791028105853.jpg",
        "date_added": "2023-05-13T06:45:04.512Z"
    },
    {
        "isbn": "9791038204089",
        "title": "La limite n'a pas de connerie",
        "author": "Emmanuel Reuzé",
        "publisher": "Fluide glacial",
        "published": "2022-04-06",
        "year": 2022,
        "format": "Grand Format",
        "genre": "Bandes dessinées & Comics",
        "pages": null,
        "read": true,
        "rating": 0,
        "comment": "",
        "gleeph_url": "https://www.gleeph.com/book/ean/9791038204089",
        "image": "books-cover/9791038204089.jpg",
        "date_added": "2023-05-13T06:45:04.512Z"
    },
    {
        "isbn": "9782409036095",
        "title": "Green IT : les clés pour des projets informatiques plus responsables",
        "author": "Margerie Guilliot, Raphaël Lemaire, Sylvain Revereault",
        "publisher": "ENI",
        "published": "2022-06-08",
        "year": 2022,
        "format": "Grand Format",
        "genre": "Éducation & Savoirs",
        "pages": null,
        "read": false,
        "rating": 0,
        "comment": "",
        "gleeph_url": "https://www.gleeph.com/book/ean/9782409036095",
        "image": "books-cover/9782409036095.jpg",
        "date_added": "2023-05-13T06:45:04.512Z"
    },
    {
        "isbn": "9782302044814",
        "title": "Elfes. Vol. 10. Elfe noir, coeur sombre",
        "author": "Hadrien, Yi Ma",
        "publisher": "Soleil",
        "published": "2015-05-21",
        "year": 2015,
        "format": "Grand Format",
        "genre": "Bandes dessinées & Comics",
        "pages": null,
        "read": false,
        "rating": 0,
        "comment": "",
        "gleeph_url": "https://www.gleeph.com/book/ean/9782302044814",
        "image": "books-cover/9782302044814.jpg",
        "date_added": "2023-05-13T06:39:27.514Z"
    },
    {
        "isbn": "9782302043442",
        "title": "Elfes. Vol. 9. Le siège de Cadanla",
        "author": "Eric Corbeyran, Gwendal Lemercier",
        "publisher": "Soleil",
        "published": "2015-05-21",
        "year": 2015,
        "format": "Grand Format",
        "genre": "Bandes dessinées & Comics",
        "pages": null,
        "read": false,
        "rating": 0,
        "comment": "",
        "gleeph_url": "https://www.gleeph.com/book/ean/9782302043442",
        "image": "books-cover/9782302043442.jpg",
        "date_added": "2023-05-13T06:39:19.838Z"
    },
    {
        "isbn": "9782302042735",
        "title": "Elfes. Vol. 8. La dernière ombre",
        "author": "Olivier Peru, Stéphane Bileau",
        "publisher": "Soleil",
        "published": "2014-10-22",
        "year": 2014,
        "format": "Grand Format",
        "genre": "Bandes dessinées & Comics",
        "pages": null,
        "read": false,
        "rating": 0,
        "comment": "",
        "gleeph_url": "https://www.gleeph.com/book/ean/9782302042735",
        "image": "books-cover/9782302042735.jpg",
        "date_added": "2023-05-13T06:39:16.104Z"
    },
    {
        "isbn": "9782302042049",
        "title": "Elfes. Vol. 7. Le crystal des elfes sylvains",
        "author": "Nicolas Jarry, Gianluca Maconi",
        "publisher": "Soleil",
        "published": "2014-08-20",
        "year": 2014,
        "format": "Grand Format",
        "genre": "Bandes dessinées & Comics",
        "pages": null,
        "read": false,
        "rating": 0,
        "comment": "",
        "gleeph_url": "https://www.gleeph.com/book/ean/9782302042049",
        "image": "books-cover/9782302042049.jpg",
        "date_added": "2023-05-13T06:39:11.716Z"
    },
    {
        "isbn": "9782302038295",
        "title": "Elfes. Vol. 6. La mission des elfes bleus",
        "author": "Jean-Luc Istin, Kyko Duarte",
        "publisher": "Soleil",
        "published": "2015-05-21",
        "year": 2015,
        "format": "Grand Format",
        "genre": "Bandes dessinées & Comics",
        "pages": null,
        "read": false,
        "rating": 0,
        "comment": "",
        "gleeph_url": "https://www.gleeph.com/book/ean/9782302038295",
        "image": "books-cover/9782302038295.jpg",
        "date_added": "2023-05-13T06:39:07.278Z"
    },
    {
        "isbn": "9782302036925",
        "title": "Elfes. Vol. 5. La dynastie des elfes noirs",
        "author": "Christophe Arleston, Yi Ma",
        "publisher": "Soleil",
        "published": "2015-05-21",
        "year": 2015,
        "format": "Grand Format",
        "genre": "Bandes dessinées & Comics",
        "pages": null,
        "read": false,
        "rating": 0,
        "comment": "",
        "gleeph_url": "https://www.gleeph.com/book/ean/9782302036925",
        "image": "books-cover/9782302036925.jpg",
        "date_added": "2023-05-13T06:39:03.258Z"
    },
    {
        "isbn": "9782302030893",
        "title": "Elfes. Vol. 4. L'élu des semi-elfes",
        "author": "Eric Corbeyran, Jean-Paul Bordier",
        "publisher": "Soleil",
        "published": "2015-05-21",
        "year": 2015,
        "format": "Grand Format",
        "genre": "Bandes dessinées & Comics",
        "pages": null,
        "read": false,
        "rating": 0,
        "comment": "",
        "gleeph_url": "https://www.gleeph.com/book/ean/9782302030893",
        "image": "books-cover/9782302030893.jpg",
        "date_added": "2023-05-13T06:38:59.127Z"
    },
    {
        "isbn": "9782302030596",
        "title": "Elfes. Vol. 3. Elfe blanc, coeur noir",
        "author": "Olivier Peru, Stéphane Bileau",
        "publisher": "Soleil",
        "published": "2015-05-29",
        "year": 2015,
        "format": "Grand Format",
        "genre": "Bandes dessinées & Comics",
        "pages": null,
        "read": false,
        "rating": 0,
        "comment": "",
        "gleeph_url": "https://www.gleeph.com/book/ean/9782302030596",
        "image": "books-cover/9782302030596.jpg",
        "date_added": "2023-05-13T06:38:54.143Z"
    },
    {
        "isbn": "9782302024946",
        "title": "Elfes. Vol. 2. L'honneur des elfes sylvains",
        "author": "Nicolas Jarry, Gianluca Maconi",
        "publisher": "Soleil",
        "published": "2015-05-29",
        "year": 2015,
        "format": "Grand Format",
        "genre": "Bandes dessinées & Comics",
        "pages": null,
        "read": false,
        "rating": 0,
        "comment": "",
        "gleeph_url": "https://www.gleeph.com/book/ean/9782302024946",
        "image": "books-cover/9782302024946.jpg",
        "date_added": "2023-05-13T06:38:43.965Z"
    },
    {
        "isbn": "9782302027190",
        "title": "Elfes. Vol. 1. Le crystal des elfes bleus",
        "author": "Jean-Luc Istin, Kyko Duarte",
        "publisher": "Soleil",
        "published": "2015-05-21",
        "year": 2015,
        "format": "Grand Format",
        "genre": "Bandes dessinées & Comics",
        "pages": null,
        "read": true,
        "rating": 0,
        "comment": "",
        "gleeph_url": "https://www.gleeph.com/book/ean/9782302027190",
        "image": "books-cover/9782302027190.jpg",
        "date_added": "2023-05-13T06:38:14.129Z"
    },
    {
        "isbn": "9782205088168",
        "title": "Le monde sans fin",
        "author": "Jean-Marc Jancovici, Christophe Blain",
        "publisher": "Dargaud",
        "published": "2021-10-29",
        "year": 2021,
        "format": "Grand Format",
        "genre": "Bandes dessinées & Comics",
        "pages": null,
        "read": false,
        "rating": 0,
        "comment": "",
        "gleeph_url": "https://www.gleeph.com/book/ean/9782205088168",
        "image": "books-cover/9782205088168.jpg",
        "date_added": "2023-05-13T06:36:53.798Z"
    },
    {
        "isbn": "9781491973899",
        "title": "The Manager's Path",
        "author": "Camille Fournier",
        "publisher": "O'Reilly Media",
        "published": "2017-01-01",
        "year": 2017,
        "format": "Grand Format",
        "genre": "Art, Culture & Société",
        "pages": null,
        "read": true,
        "rating": 0,
        "comment": "",
        "gleeph_url": "https://www.gleeph.com/book/ean/9781491973899",
        "image": "books-cover/9781491973899.jpg",
        "date_added": "2023-05-13T06:36:53.798Z"
    },
    {
        "isbn": "9782203088054",
        "title": "Transperceneige : intégrale",
        "author": "Jacques Lob, Benjamin Legrand, Jean-Marc Rochette",
        "publisher": "Casterman",
        "published": "2014-03-26",
        "year": 2014,
        "format": "Grand Format",
        "genre": "Bandes dessinées & Comics",
        "pages": null,
        "read": true,
        "rating": 0,
        "comment": "",
        "gleeph_url": "https://www.gleeph.com/book/ean/9782203088054",
        "image": "books-cover/9782203088054.jpg",
        "date_added": "2023-05-13T06:36:53.798Z"
    },
    {
        "isbn": "9782302071308",
        "title": "Conquêtes. Vol. 1. Islandia",
        "author": "Jean-Luc Istin, Zivorad Radivojevic",
        "publisher": "Soleil",
        "published": "2019-07-18",
        "year": 2019,
        "format": "Grand Format",
        "genre": "Bandes dessinées & Comics",
        "pages": null,
        "read": true,
        "rating": 0,
        "comment": "",
        "gleeph_url": "https://www.gleeph.com/book/ean/9782302071308",
        "image": "books-cover/9782302071308.jpg",
        "date_added": "2023-05-13T06:36:53.798Z"
    },
    {
        "isbn": "9782344044353",
        "title": "Sang royal : intégrale",
        "author": "Alexandro Jodorowsky, Dongzi Liu",
        "publisher": "Glénat",
        "published": "2020-10-28",
        "year": 2020,
        "format": "Grand Format",
        "genre": "Bandes dessinées & Comics",
        "pages": null,
        "read": true,
        "rating": 0,
        "comment": "",
        "gleeph_url": "https://www.gleeph.com/book/ean/9782344044353",
        "image": "books-cover/9782344044353.jpg",
        "date_added": "2023-05-13T06:36:53.798Z"
    },
    {
        "isbn": "9782359109696",
        "title": "Shangri-La",
        "author": "Mathieu Bablet",
        "publisher": "Ankama",
        "published": "2016-09-02",
        "year": 2016,
        "format": "Grand Format",
        "genre": "Bandes dessinées & Comics",
        "pages": null,
        "read": true,
        "rating": 0,
        "comment": "",
        "gleeph_url": "https://www.gleeph.com/book/ean/9782359109696",
        "image": "books-cover/9782359109696.jpg",
        "date_added": "2023-05-13T06:36:53.798Z"
    },
    {
        "isbn": "9782377316588",
        "title": "1984",
        "author": "Xavier Coste",
        "publisher": "Sarbacane",
        "published": "2021-02-16",
        "year": 2021,
        "format": "Grand Format",
        "genre": "Bandes dessinées & Comics",
        "pages": null,
        "read": true,
        "rating": 0,
        "comment": "",
        "gleeph_url": "https://www.gleeph.com/book/ean/9782377316588",
        "image": "books-cover/9782377316588.jpg",
        "date_added": "2023-05-13T06:36:53.798Z"
    },
    {
        "isbn": "9791033512424",
        "title": "Carbone & Silicium",
        "author": "Mathieu Bablet",
        "publisher": "Ankama",
        "published": "2022-05-20",
        "year": 2022,
        "format": "Grand Format",
        "genre": "Bandes dessinées & Comics",
        "pages": null,
        "read": true,
        "rating": 0,
        "comment": "",
        "gleeph_url": "https://www.gleeph.com/book/ean/9791033512424",
        "image": "books-cover/9791033512424.jpg",
        "date_added": "2023-05-13T06:36:53.798Z"
    },
    {
        "isbn": "9780241448304",
        "title": "HOW TO AVOID A CLIMATE DISASTER",
        "author": "Bill Gates",
        "publisher": "Penguin",
        "published": "2021-02-15",
        "year": 2021,
        "format": "Grand Format",
        "genre": "Éducation & Savoirs",
        "pages": null,
        "read": false,
        "rating": 0,
        "comment": "",
        "gleeph_url": "https://www.gleeph.com/book/ean/9780241448304",
        "image": "books-cover/9780241448304.jpg",
        "date_added": "2023-05-13T06:36:53.798Z"
    },
    {
        "isbn": "9781942788768",
        "title": "The Unicorn Project",
        "author": "Gene Kim",
        "publisher": "IT Revolution",
        "published": "2019-11-26",
        "year": 2019,
        "format": "Grand Format",
        "genre": "Éducation & Savoirs",
        "pages": null,
        "read": false,
        "rating": 0,
        "comment": "",
        "gleeph_url": "https://www.gleeph.com/book/ean/9781942788768",
        "image": "books-cover/9781942788768.jpg",
        "date_added": "2023-05-13T06:36:53.798Z"
    },
    {
        "isbn": "9782302074101",
        "title": "Conquêtes. Vol. 2. Deluvenn",
        "author": "Nicolas Jarry, Bertrand Benoît",
        "publisher": "Soleil",
        "published": "2019-07-18",
        "year": 2019,
        "format": "Grand Format",
        "genre": "Bandes dessinées & Comics",
        "pages": null,
        "read": false,
        "rating": 0,
        "comment": "",
        "gleeph_url": "https://www.gleeph.com/book/ean/9782302074101",
        "image": "books-cover/9782302074101.jpg",
        "date_added": "2023-05-13T06:36:53.798Z"
    },
    {
        "isbn": "9791036313691",
        "title": "L'héritage. Vol. 1. Eragon",
        "author": "Christopher Paolini",
        "publisher": "Bayard Jeunesse",
        "published": "2019-09-18",
        "year": 2019,
        "format": "Poche",
        "genre": "Jeunes adultes",
        "pages": null,
        "read": true,
        "rating": 0,
        "comment": "",
        "gleeph_url": "https://www.gleeph.com/book/ean/9791036313691",
        "image": "books-cover/9791036313691.jpg",
        "date_added": "2023-05-13T06:26:18.752Z"
    },
    {
        "isbn": "9782203103993",
        "title": "Gloutons & dragons. Vol. 1",
        "author": "Ryoko Kui",
        "publisher": "Casterman",
        "published": "2017-05-17",
        "year": 2017,
        "format": "Poche",
        "genre": "Mangas",
        "pages": null,
        "read": true,
        "rating": 0,
        "comment": "",
        "gleeph_url": "https://www.gleeph.com/book/ean/9782203103993",
        "image": "books-cover/9782203103993.jpg",
        "date_added": "2023-05-08T07:04:54.587Z"
    },
    {
        "isbn": "9782359101256",
        "title": "Freaks' squeele. Vol. 4. Succube pizza",
        "author": "Florent Maudoux",
        "publisher": "Ankama",
        "published": "2011-01-27",
        "year": 2011,
        "format": "Grand Format",
        "genre": "Bandes dessinées & Comics",
        "pages": null,
        "read": false,
        "rating": 0,
        "comment": "",
        "gleeph_url": "https://www.gleeph.com/book/ean/9782359101256",
        "image": "books-cover/9782359101256.jpg",
        "date_added": "2023-05-13T06:24:16.405Z"
    },
    {
        "isbn": "9782298154122",
        "title": "Le sorceleur - Tome 2",
        "author": "Andrzej Sapkowski",
        "publisher": "Auto-édition",
        "published": "2019-01-01",
        "year": 2019,
        "format": "",
        "genre": "Imaginaire",
        "pages": null,
        "read": false,
        "rating": 0,
        "comment": "",
        "gleeph_url": "https://www.gleeph.com/book/ean/9782298154122",
        "image": "books-cover/9782298154122.jpg",
        "date_added": "2023-05-10T09:50:20.973Z"
    },
    {
        "isbn": "9782298151916",
        "title": "Le sorceleur - Tome 1",
        "author": "Andrzej Sapkowski",
        "publisher": "Auto-édition",
        "published": "2019-01-01",
        "year": 2019,
        "format": "",
        "genre": "Imaginaire",
        "pages": null,
        "read": true,
        "rating": 0,
        "comment": "",
        "gleeph_url": "https://www.gleeph.com/book/ean/9782298151916",
        "image": "books-cover/9782298151916.jpg",
        "date_added": "2023-05-10T09:50:09.757Z"
    },
    {
        "isbn": "9782266182690",
        "title": "Hunger games. Vol. 1",
        "author": "Suzanne Collins",
        "publisher": "Pocket jeunesse",
        "published": "2009-10-01",
        "year": 2009,
        "format": "Grand Format",
        "genre": "Jeunes adultes",
        "pages": null,
        "read": true,
        "rating": 0,
        "comment": "",
        "gleeph_url": "https://www.gleeph.com/book/ean/9782266182690",
        "image": "books-cover/9782266182690.jpg",
        "date_added": "2023-05-08T07:03:27.079Z"
    }
]
